HISTORY.rst
LICENSE
MANIFEST.in
README.rst
setup.cfg
setup.py
tif2geojson.py
tif2geojson.egg-info/PKG-INFO
tif2geojson.egg-info/SOURCES.txt
tif2geojson.egg-info/dependency_links.txt
tif2geojson.egg-info/not-zip-safe
tif2geojson.egg-info/requires.txt
tif2geojson.egg-info/top_level.txt