Metadata-Version: 1.1
Name: tif2geojson
Version: 0.1.1
Summary: Converts TourInFrance XML format to GeoJSON
Home-page: https://github.com/makinacorpus/tif2geojson
Author: Makina Corpus
Author-email: mathieu.leplatre@makina-corpus.com
License: BSD
Keywords: tif2geojson
Platform: UNKNOWN
Classifier: Development Status :: 2 - Pre-Alpha
Classifier: Intended Audience :: Developers
Classifier: License :: OSI Approved :: BSD License
Classifier: Natural Language :: English
Classifier: Programming Language :: Python :: 2
Classifier: Programming Language :: Python :: 2.6
Classifier: Programming Language :: Python :: 2.7
Classifier: Programming Language :: Python :: 3
Classifier: Programming Language :: Python :: 3.3
